{
  "version": "7",
  "dialect": "postgresql",
  "entries": [
    {
      "idx": 0,
      "version": "7",
      "when": 1773284677128,
      "tag": "0000_condemned_amazoness",
      "breakpoints": true
    },
    {
      "idx": 1,
      "version": "7",
      "when": 1773286063887,
      "tag": "0001_romantic_metal_master",
      "breakpoints": true
    },
    {
      "idx": 2,
      "version": "7",
      "when": 1773296930990,
      "tag": "0002_deep_starbolt",
      "breakpoints": true
    },
    {
      "idx": 3,
      "version": "7",
      "when": 1773300046969,
      "tag": "0003_demonic_jamie_braddock",
      "breakpoints": true
    },
    {
      "idx": 4,
      "version": "7",
      "when": 1773307968028,
      "tag": "0004_same_punisher",
      "breakpoints": true
    },
    {
      "idx": 5,
      "version": "7",
      "when": 1773314325134,
      "tag": "0005_tiny_ravenous",
      "breakpoints": true
    },
    {
      "idx": 6,
      "version": "7",
      "when": 1773341641870,
      "tag": "0006_boring_blackheart",
      "breakpoints": true
    },
    {
      "idx": 7,
      "version": "7",
      "when": 1773342967916,
      "tag": "0007_brainy_forgotten_one",
      "breakpoints": true
    },
    {
      "idx": 8,
      "version": "7",
      "when": 1773346956824,
      "tag": "0008_giant_hitman",
      "breakpoints": true
    },
    {
      "idx": 9,
      "version": "7",
      "when": 1773609600000,
      "tag": "0009_rls_all_tables",
      "breakpoints": true
    },
    {
      "idx": 10,
      "version": "7",
      "when": 1773619200000,
      "tag": "0010_field_type_not_null",
      "breakpoints": true
    }
  ]
}
